imp3/__init__.py
imp3/app.py
imp3/cleaning_app.py
imp3/run.py
tests/__init__.py
tests/unit_test.py
imp3-0.1.4.dist-info/LICENSE
imp3-0.1.4.dist-info/METADATA
imp3-0.1.4.dist-info/WHEEL
imp3-0.1.4.dist-info/entry_points.txt
imp3-0.1.4.dist-info/top_level.txt
imp3-0.1.4.dist-info/RECORD
