Metadata-Version: 2.1
Name: imp3
Version: 0.1.4
Summary: Interactive tool for image pre-processing and automated pipeline creation
Home-page: https://github.com/bokey007/imp3
Author: Sudhir Arvind Deshmukh
License-File: LICENSE
Requires-Dist: matplotlib (==3.6.0)
Requires-Dist: numpy (==1.23.3)
Requires-Dist: opencv-python (==4.6.0.66)
Requires-Dist: Pillow (==9.5.0)
Requires-Dist: streamlit (==1.13.0)
